MANIFEST.in
README.md
pyproject.toml
setup.cfg
setup.py
src/first_python_package.egg-info/PKG-INFO
src/first_python_package.egg-info/SOURCES.txt
src/first_python_package.egg-info/dependency_links.txt
src/first_python_package.egg-info/entry_points.txt
src/first_python_package.egg-info/requires.txt
src/first_python_package.egg-info/top_level.txt
src/imppkg/__init__.py
src/imppkg/data.json
src/imppkg/harmonic_mean.c
src/imppkg/harmonic_mean.pyx
src/imppkg/harmony.py
src/imppkg/hello.py
src/imppkg/__pycache__/harmonic_mean.cpython-310.pyc
src/pubpypack_harmony_marcin_sztylko.egg-info/PKG-INFO
src/pubpypack_harmony_marcin_sztylko.egg-info/SOURCES.txt
src/pubpypack_harmony_marcin_sztylko.egg-info/dependency_links.txt
src/pubpypack_harmony_marcin_sztylko.egg-info/entry_points.txt
src/pubpypack_harmony_marcin_sztylko.egg-info/requires.txt
src/pubpypack_harmony_marcin_sztylko.egg-info/top_level.txt