Metadata-Version: 2.1
Name: pubpypack-harmony-marcin-sztylko
Version: 0.0.1
Summary: Test description for the first python package.
Home-page: https://github.com/msztylko/test-imports
Author: Marcin Sztylko
Author-email: marcin.sztylko@gmail.com
License: MIT
Classifier: License :: OSI Approved :: MIT License
Requires-Python: >=3.9
